{
  "ambiguitySname": "广州",
  "distance": 133563.93798094537,
  "hotelList": [],
  "hotelPrice": 390,
  "hotness": 132.3554868763605,
  "maxDay": 3,
  "minDay": 2,
  "sceneTicket": 260,
  "sceneryList": [
    {
      "ambiguitySname": "大丘园农庄",
      "fullUrl": "http://b.hiphotos.baidu.com/lvpics/w%3D300/sign=7afe98e14a36acaf59e090fc4cd88d03/5fdf8db1cb134954b83233bc574e9258d1094a3e.jpg",
      "lat": 23.625787546278,
      "lng": 113.58473371639,
      "mapX": 12644332.3,
      "mapY": 2690596.1,
      "moreDesc": "大丘园农庄前身为1993年创园的大丘有机休闲农庄。以生产仙蜜果（火龙果）为主，农场占地500多亩。 农庄占地500多亩，主要种植仙蜜果、花卉等热带植物和经营富有地方特色的餐饮业，是广州最大的仙蜜果种植基地。",
      "parentSid": "",
      "price": 0,
      "sid": "8e29baf11bc6adc41efab606",
      "sname": "大丘园农庄",
      "surl": "daqiuyuannongzhuang",
      "viewCount": 1271,
      "visitDay": 0.5
    },
    {
      "ambiguitySname": "广州动物园",
      "fullUrl": "http://e.hiphotos.baidu.com/lvpics/w%3D300/sign=9dcde950b13533faf5b6952e98d3fdca/ac0acf13f7e5d76c5aaf53a0.jpg",
      "lat": 23.147619049197,
      "lng": 113.31177702965,
      "mapX": 12613946.57,
      "mapY": 2632932.43,
      "moreDesc": "广州动物园位于先烈中路东段，兴建于1958年，总面积为43.3万平方米，是我国三大城市动物园之一。\n园内树木葱茏，花繁草茂，生机盎然，所有动物笼舍排列有序，掩映于红花绿叶之中，具有南方园林特色。\n广州动物园共有选自全国和世界各地的哺乳类、爬虫类、鸟类和鱼类等动物 450余种，4500多头（只），其中不少属于世界珍禽异兽。",
      "parentSid": "",
      "price": 20,
      "sid": "68fa7ae3b9d414ff762fddc6",
      "sname": "广州动物园",
      "surl": "guangzhoudongwuyuan",
      "viewCount": 188747,
      "visitDay": 0.25
    },
    {
      "ambiguitySname": "沙面",
      "fullUrl": "http://d.hiphotos.baidu.com/lvpics/w%3D300/sign=cf17083834a85edffa8cf823795409d8/389aa8fd2140844e09244ddb.jpg",
      "lat": 23.112766974137,
      "lng": 113.2513129841,
      "mapX": 12607215.67,
      "mapY": 2628737.71,
      "moreDesc": "沙面曾称拾翠洲。在广州城区西南，原是珠江冲积而成的沙洲，故名。\n宋、元、明、清历代为国内外通商要津和游览地。鸦片战争后，清咸丰十一年(1861年)后沦为英、法租界。现为广州重要商埠。\n沙面是广州著名的旅游区、风景区和休闲胜地。",
      "parentSid": "",
      "price": 0,
      "sid": "60193dff1e4019c66b17adf8",
      "sname": "沙面",
      "surl": "shamian",
      "viewCount": 760543,
      "visitDay": 0.25
    },
    {
      "ambiguitySname": "瀛洲生态公园",
      "fullUrl": "http://f.hiphotos.baidu.com/lvpics/w%3D300/sign=e6267c02d462853592e0d421a0ee76f2/b03533fa828ba61ed5a5cedf4034970a314e59f2.jpg",
      "lat": 23.059731017364,
      "lng": 113.36643802161,
      "mapX": 12620031.47,
      "mapY": 2622356.53,
      "moreDesc": "瀛洲生态公园位于广东省广州市海珠区辖内（南洲路以东），被人们喻为广州市的“南肺”。公园总面积142公顷，公园依傍珠江南航道，连接华南快速干线。公园范围内河涌纵横交错，蟛蜞洞穴星罗棋布。盛产各种岭南名果，其中以石硖龙眼、红果杨桃、鸡心黄皮等最盛名。",
      "parentSid": "",
      "price": 0,
      "sid": "5319dc24b39f09736a73a63b",
      "sname": "瀛洲生态公园",
      "surl": "yingzhoushengtaigongyuan",
      "viewCount": 1672,
      "visitDay": 0.5
    },
    {
      "ambiguitySname": "长隆夜间动物世界",
      "fullUrl": "http://a.hiphotos.baidu.com/lvpics/w%3D300/sign=2506182f7a899e51788e3c1472a5d990/8718367adab44aed3e8f7536b21c8701a08bfb1b.jpg",
      "lat": 23.008371670603,
      "lng": 113.3382485659,
      "mapX": 12616893.4,
      "mapY": 2616179.5,
      "moreDesc": "长隆夜间动物世界是位于中国广东省广州市番禺区迎宾路。是由同市的香江野生动物世界新组建的长隆集团投资近10亿人民币，于2000年12月开幕。作为中国首个夜间动物园，该动物园的主题是令游客可以欣赏动物在晚间时的生态。",
      "parentSid": "",
      "price": 0,
      "sid": "c2e954c85f19f4778b2d791d",
      "sname": "长隆夜间动物世界",
      "surl": "changlongyejiandongwushijie",
      "viewCount": 6237,
      "visitDay": 0.5
    },
    {
      "ambiguitySname": "长隆欢乐世界",
      "fullUrl": "http://e.hiphotos.baidu.com/lvpics/w%3D300/sign=a3787158a9ec8a13141a51e0c7029157/242dd42a2834349bf76f3b32c9ea15ce36d3be18.jpg",
      "lat": 23.005241010951,
      "lng": 113.33789903522,
      "mapX": 12616854.49,
      "mapY": 2615803.05,
      "moreDesc": "长隆欢乐世界地处广州番禺迎宾路，游乐设施有近70项。\n欢乐世界引进了瑞士、荷兰、德国、意大利、美国等全球领先的游乐设备公司的设备，其中包括：垂直过山车， 十环过山车、摩托过山车、U型摩天滑板和超级水车大战等。",
      "parentSid": "",
      "price": 200,
      "sid": "bd47bc1a34e1c43404a652f8",
      "sname": "长隆欢乐世界",
      "surl": "changlonghuanleshijie",
      "viewCount": 766324,
      "visitDay": 0.5
    },
    {
      "ambiguitySname": "宝墨园",
      "fullUrl": "http://b.hiphotos.baidu.com/lvpics/w%3D300/sign=5f8f5eeb0f2442a7ae0efba5e142ad95/6398ecd396f24087a8ec9a1c.jpg",
      "lat": 22.901170980612,
      "lng": 113.30078401597,
      "mapX": 12612722.82,
      "mapY": 2603294.04,
      "moreDesc": "宝墨园位于广东省番禺市西南部的沙湾镇紫坭村内，距离番禹市区10余公里。集清官文化、岭南古建筑、岭南园林艺术、珠三角水乡特色于一体。\n宝墨园四时青翠，百卉丛开，园林花卉景点，有聚有散，步移景换，美不胜收。",
      "parentSid": "",
      "price": 40,
      "sid": "e4ce7454b0656bc57594bef8",
      "sname": "宝墨园",
      "surl": "baomoyuan",
      "viewCount": 186384,
      "visitDay": 0.25
    },
    {
      "ambiguitySname": "番禺莲花山",
      "fullUrl": "http://b.hiphotos.baidu.com/lvpics/w%3D300/sign=a9dda56eafc379317d688029dbc4b784/b3ba5d16bc0f1d1220a4e9a3.jpg",
      "lat": 22.99008897742,
      "lng": 113.51030703881,
      "mapX": 12636047.07,
      "mapY": 2613981.2,
      "moreDesc": "番禺莲花山是广东省重点风景名胜区，位于广州市番禺区东部珠江口狮子河畔。莲花山由48座红色砂岩低山组成，海拔最高为108米，占地2.54平方公里。其中有座麒麟峰，因峰顶上有一块酷似莲花的岩石，所以后人把这座山称为莲花山。",
      "parentSid": "",
      "price": 0,
      "sid": "dbfa1bc6adc41efa15d8b7f8",
      "sname": "莲花山",
      "surl": "fanyulianhuashan",
      "viewCount": 328703,
      "visitDay": 0.25
    }
  ],
  "sid": "da666bc57594baeb76b3bcf0",
  "sname": "广州",
  "sumPrice": 650,
  "surl": "guangzhou",
  "uid": "5d1078c25ea66122a71f5b2a494ccb95",
  "viewCount": 279985,
  "visitDay": 3,
  "arrange": [
    {
      "list": [
        {
          "ambiguitySname": "大丘园农庄",
          "fullUrl": "http://b.hiphotos.baidu.com/lvpics/w%3D300/sign=7afe98e14a36acaf59e090fc4cd88d03/5fdf8db1cb134954b83233bc574e9258d1094a3e.jpg",
          "lat": 23.625787546278,
          "lng": 113.58473371639,
          "mapX": 12644332.3,
          "mapY": 2690596.1,
          "moreDesc": "大丘园农庄前身为1993年创园的大丘有机休闲农庄。以生产仙蜜果（火龙果）为主，农场占地500多亩。 农庄占地500多亩，主要种植仙蜜果、花卉等热带植物和经营富有地方特色的餐饮业，是广州最大的仙蜜果种植基地。",
          "parentSid": "",
          "price": 0,
          "sid": "8e29baf11bc6adc41efab606",
          "sname": "大丘园农庄",
          "surl": "daqiuyuannongzhuang",
          "viewCount": 1271,
          "visitDay": 0.5
        },
        {
          "ambiguitySname": "广州动物园",
          "fullUrl": "http://e.hiphotos.baidu.com/lvpics/w%3D300/sign=9dcde950b13533faf5b6952e98d3fdca/ac0acf13f7e5d76c5aaf53a0.jpg",
          "lat": 23.147619049197,
          "lng": 113.31177702965,
          "mapX": 12613946.57,
          "mapY": 2632932.43,
          "moreDesc": "广州动物园位于先烈中路东段，兴建于1958年，总面积为43.3万平方米，是我国三大城市动物园之一。\n园内树木葱茏，花繁草茂，生机盎然，所有动物笼舍排列有序，掩映于红花绿叶之中，具有南方园林特色。\n广州动物园共有选自全国和世界各地的哺乳类、爬虫类、鸟类和鱼类等动物 450余种，4500多头（只），其中不少属于世界珍禽异兽。",
          "parentSid": "",
          "price": 20,
          "sid": "68fa7ae3b9d414ff762fddc6",
          "sname": "广州动物园",
          "surl": "guangzhoudongwuyuan",
          "viewCount": 188747,
          "visitDay": 0.25
        },
        {
          "ambiguitySname": "沙面",
          "fullUrl": "http://d.hiphotos.baidu.com/lvpics/w%3D300/sign=cf17083834a85edffa8cf823795409d8/389aa8fd2140844e09244ddb.jpg",
          "lat": 23.112766974137,
          "lng": 113.2513129841,
          "mapX": 12607215.67,
          "mapY": 2628737.71,
          "moreDesc": "沙面曾称拾翠洲。在广州城区西南，原是珠江冲积而成的沙洲，故名。\n宋、元、明、清历代为国内外通商要津和游览地。鸦片战争后，清咸丰十一年(1861年)后沦为英、法租界。现为广州重要商埠。\n沙面是广州著名的旅游区、风景区和休闲胜地。",
          "parentSid": "",
          "price": 0,
          "sid": "60193dff1e4019c66b17adf8",
          "sname": "沙面",
          "surl": "shamian",
          "viewCount": 760543,
          "visitDay": 0.25
        }
      ],
      "curDay": "第1天",
      "hotel": {
        "commentCount": 0,
        "commentScore": 4.7,
        "hotelAddress": "越秀区海珠中路215号全幢",
        "hotelName": "春田家家青年旅舍",
        "lat": 23.12414895967027,
        "lng": 113.26277122523088,
        "phone": "(020)81923232",
        "pic": "http://t12.baidu.com/it/u=3068265737,395595340&fm=22",
        "price": 80,
        "sid": "60193dff1e4019c66b17adf8",
        "uid": "8e3bd5338ed6d4738c55ec75"
      }
    },
    {
      "list": [
        {
          "ambiguitySname": "瀛洲生态公园",
          "fullUrl": "http://f.hiphotos.baidu.com/lvpics/w%3D300/sign=e6267c02d462853592e0d421a0ee76f2/b03533fa828ba61ed5a5cedf4034970a314e59f2.jpg",
          "lat": 23.059731017364,
          "lng": 113.36643802161,
          "mapX": 12620031.47,
          "mapY": 2622356.53,
          "moreDesc": "瀛洲生态公园位于广东省广州市海珠区辖内（南洲路以东），被人们喻为广州市的“南肺”。公园总面积142公顷，公园依傍珠江南航道，连接华南快速干线。公园范围内河涌纵横交错，蟛蜞洞穴星罗棋布。盛产各种岭南名果，其中以石硖龙眼、红果杨桃、鸡心黄皮等最盛名。",
          "parentSid": "",
          "price": 0,
          "sid": "5319dc24b39f09736a73a63b",
          "sname": "瀛洲生态公园",
          "surl": "yingzhoushengtaigongyuan",
          "viewCount": 1672,
          "visitDay": 0.5
        },
        {
          "ambiguitySname": "长隆夜间动物世界",
          "fullUrl": "http://a.hiphotos.baidu.com/lvpics/w%3D300/sign=2506182f7a899e51788e3c1472a5d990/8718367adab44aed3e8f7536b21c8701a08bfb1b.jpg",
          "lat": 23.008371670603,
          "lng": 113.3382485659,
          "mapX": 12616893.4,
          "mapY": 2616179.5,
          "moreDesc": "长隆夜间动物世界是位于中国广东省广州市番禺区迎宾路。是由同市的香江野生动物世界新组建的长隆集团投资近10亿人民币，于2000年12月开幕。作为中国首个夜间动物园，该动物园的主题是令游客可以欣赏动物在晚间时的生态。",
          "parentSid": "",
          "price": 0,
          "sid": "c2e954c85f19f4778b2d791d",
          "sname": "长隆夜间动物世界",
          "surl": "changlongyejiandongwushijie",
          "viewCount": 6237,
          "visitDay": 0.5
        }
      ],
      "curDay": "第2天",
      "hotel": {
        "commentCount": 0,
        "commentScore": 4.7,
        "hotelAddress": "番禺区南村镇塘步西村塘西工业园B1栋（塘西路与龙山大道交叉口）",
        "hotelName": "广州百越居商务酒店)",
        "lat": 23.01579838385788,
        "lng": 113.34631357938837,
        "phone": "(020)66318098",
        "pic": "http://t10.baidu.com/it/u=3402970269,3148529503&fm=22",
        "price": 157,
        "sid": "c2e954c85f19f4778b2d791d",
        "uid": "cc459564eadf650300ff2d20"
      }
    },
    {
      "list": [
        {
          "ambiguitySname": "长隆欢乐世界",
          "fullUrl": "http://e.hiphotos.baidu.com/lvpics/w%3D300/sign=a3787158a9ec8a13141a51e0c7029157/242dd42a2834349bf76f3b32c9ea15ce36d3be18.jpg",
          "lat": 23.005241010951,
          "lng": 113.33789903522,
          "mapX": 12616854.49,
          "mapY": 2615803.05,
          "moreDesc": "长隆欢乐世界地处广州番禺迎宾路，游乐设施有近70项。\n欢乐世界引进了瑞士、荷兰、德国、意大利、美国等全球领先的游乐设备公司的设备，其中包括：垂直过山车， 十环过山车、摩托过山车、U型摩天滑板和超级水车大战等。",
          "parentSid": "",
          "price": 200,
          "sid": "bd47bc1a34e1c43404a652f8",
          "sname": "长隆欢乐世界",
          "surl": "changlonghuanleshijie",
          "viewCount": 766324,
          "visitDay": 0.5
        },
        {
          "ambiguitySname": "宝墨园",
          "fullUrl": "http://b.hiphotos.baidu.com/lvpics/w%3D300/sign=5f8f5eeb0f2442a7ae0efba5e142ad95/6398ecd396f24087a8ec9a1c.jpg",
          "lat": 22.901170980612,
          "lng": 113.30078401597,
          "mapX": 12612722.82,
          "mapY": 2603294.04,
          "moreDesc": "宝墨园位于广东省番禺市西南部的沙湾镇紫坭村内，距离番禹市区10余公里。集清官文化、岭南古建筑、岭南园林艺术、珠三角水乡特色于一体。\n宝墨园四时青翠，百卉丛开，园林花卉景点，有聚有散，步移景换，美不胜收。",
          "parentSid": "",
          "price": 40,
          "sid": "e4ce7454b0656bc57594bef8",
          "sname": "宝墨园",
          "surl": "baomoyuan",
          "viewCount": 186384,
          "visitDay": 0.25
        },
        {
          "ambiguitySname": "番禺莲花山",
          "fullUrl": "http://b.hiphotos.baidu.com/lvpics/w%3D300/sign=a9dda56eafc379317d688029dbc4b784/b3ba5d16bc0f1d1220a4e9a3.jpg",
          "lat": 22.99008897742,
          "lng": 113.51030703881,
          "mapX": 12636047.07,
          "mapY": 2613981.2,
          "moreDesc": "番禺莲花山是广东省重点风景名胜区，位于广州市番禺区东部珠江口狮子河畔。莲花山由48座红色砂岩低山组成，海拔最高为108米，占地2.54平方公里。其中有座麒麟峰，因峰顶上有一块酷似莲花的岩石，所以后人把这座山称为莲花山。",
          "parentSid": "",
          "price": 0,
          "sid": "dbfa1bc6adc41efa15d8b7f8",
          "sname": "莲花山",
          "surl": "fanyulianhuashan",
          "viewCount": 328703,
          "visitDay": 0.25
        }
      ],
      "curDay": "第3天",
      "hotel": {
        "commentCount": 0,
        "commentScore": 3.9,
        "hotelAddress": "莲花西路桃花路路口附近",
        "hotelName": "莲花度假山庄(酒店)",
        "lat": 22.98715145835111,
        "lng": 113.49993269750097,
        "phone": "(020)61936688",
        "pic": "http://t11.baidu.com/it/u=2422918177,3028703273&fm=22",
        "price": 138,
        "sid": "dbfa1bc6adc41efa15d8b7f8",
        "uid": "15a93810b4e7cca414c8f61e"
      }
    }
  ]
}